trusted_log/__init__.py
trusted_log/tlog_chain.py
trusted_log-0.1.1.dist-info/METADATA
trusted_log-0.1.1.dist-info/WHEEL
trusted_log-0.1.1.dist-info/top_level.txt
trusted_log-0.1.1.dist-info/RECORD
