Metadata-Version: 2.4
Name: trusted_log
Version: 0.1.1
Summary: trusted_log provides transparency log-related APIs to complete behavioral recording throughout the entire lifecycle of Docker container images, including building, uploading, downloading, and deployment.
Home-page: https://github.com/Hsy-Intel/trusted-log
Author: Siyuan Hui
Author-email: Siyuan Hui <siyuan.hui@intel.com>
Requires-Python: >=3.6
Requires-Dist: sigstore>=1.0.0
Dynamic: author
Dynamic: home-page
Dynamic: requires-python
